{"users":[{"id":1747902332940,"nom":"Hénocque","prenom":"Grégoire","avatar":"","created":1747902332940,"deleted":true},{"id":1747902343646,"nom":"Bonard","prenom":"Gilles","avatar":"","created":1747902343646,"deleted":true},{"id":1747911076742,"nom":"Grand","prenom":"Thomas","avatar":"","created":1747911076742},{"id":1747911081200,"nom":"-","prenom":"Gilles","avatar":"","created":1747911081200},{"id":1747911086040,"nom":"-","prenom":"Alan","avatar":"","created":1747911086040},{"id":1747911091293,"nom":"-","prenom":"Audrey","avatar":"","created":1747911091293},{"id":1747911096983,"nom":"-","prenom":"Grégoire","avatar":"","created":1747911096983},{"id":1747911104674,"nom":"-","prenom":"James","avatar":"","created":1747911104674},{"id":1747911109972,"nom":"-","prenom":"Nico","avatar":"","created":1747911109972},{"id":1747911116103,"nom":"-","prenom":"Romu","avatar":"","created":1747911116103},{"id":1747911121436,"nom":"-","prenom":"Damiens","avatar":"","created":1747911121436}],"produits":[{"id":1,"nom":"Barre chocolatée","prix":1,"stock":30,"stockInitial":30,"seuil":5,"created":1747906791398},{"id":2,"nom":"Boisson 1 €","prix":1,"stock":30,"stockInitial":30,"seuil":5,"created":1747906791398},{"id":3,"nom":"Boisson 2 €","prix":2,"stock":29,"stockInitial":30,"seuil":5,"created":1747906791398}],"achats":[{"id":"_edb94arup","userId":1747902343646,"produits":[{"prodId":3,"nom":"Boisson 2 €","qte":1,"prix":2}],"total":2,"date":1747906796335,"paye":true,"mode":"payé"}],"paiements":[],"settings":{"mdpAdmin":"adm","mdpStock":"sto","assoTitle":"Gestion de stock Association","logo":"","couleurs":{"accent":"#2b7a78","main_bg":"#f7f7fa"}}}